sqldbclient/__init__.py
sqldbclient/db_inspector/__init__.py
sqldbclient/db_inspector/db_inspector.py
sqldbclient/dialects/__init__.py
sqldbclient/dialects/postgresql/__init__.py
sqldbclient/dialects/postgresql/utils.py
sqldbclient/dialects/postgresql/sql_view_factory/__init__.py
sqldbclient/dialects/postgresql/sql_view_factory/pg_info_queries.py
sqldbclient/dialects/postgresql/sql_view_factory/sql_view_factory.py
sqldbclient/dialects/postgresql/sql_view_factory/view.py
sqldbclient/dialects/postgresql/sql_view_materializer/__init__.py
sqldbclient/dialects/postgresql/sql_view_materializer/sql_view_materializer.py
sqldbclient/dialects/postgresql/sql_view_materializer/sql_view_materializer_utils.py
sqldbclient/sql_asyncio/__init__.py
sqldbclient/sql_asyncio/sql_async_executor/__init__.py
sqldbclient/sql_asyncio/sql_async_executor/sql_async_executor.py
sqldbclient/sql_asyncio/sql_async_planner/__init__.py
sqldbclient/sql_asyncio/sql_async_planner/sql_async_planner.py
sqldbclient/sql_engine_factory/__init__.py
sqldbclient/sql_engine_factory/sql_engine_factory.py
sqldbclient/sql_executor/__init__.py
sqldbclient/sql_executor/sql_executor.py
sqldbclient/sql_executor/sql_executor_builder/__init__.py
sqldbclient/sql_executor/sql_executor_builder/parameter_not_specified_exception.py
sqldbclient/sql_executor/sql_executor_builder/sql_executor_builder.py
sqldbclient/sql_executor/sql_executor_config/__init__.py
sqldbclient/sql_executor/sql_executor_config/sql_executor_config.py
sqldbclient/sql_history_manager/__init__.py
sqldbclient/sql_history_manager/orm_config.py
sqldbclient/sql_history_manager/sql_history_manager.py
sqldbclient/sql_history_manager/tables/__init__.py
sqldbclient/sql_history_manager/tables/executed_sql_query/__init__.py
sqldbclient/sql_history_manager/tables/executed_sql_query/executed_sql_query.py
sqldbclient/sql_history_manager/tables/executed_sql_query_result/__init__.py
sqldbclient-0.1.2.dist-info/LICENSE
sqldbclient-0.1.2.dist-info/METADATA
sqldbclient-0.1.2.dist-info/WHEEL
sqldbclient-0.1.2.dist-info/top_level.txt
sqldbclient-0.1.2.dist-info/RECORD
