Metadata-Version: 2.1
Name: sqldbclient
Version: 0.1.2
Summary: A SQL client software package, mainly for use in Jupyter Notebook environment
Home-page: https://github.com/YuriyKozhev/SqlDBClient
Author: Yuriy Kozhev
Author-email: Yuriy Kozhev <yuriy.kozhev@gmail.com>
License: Copyright (c) 2022 Yuriy Kozhev
Project-URL: Homepage, https://github.com/YuriyKozhev/SqlDBClient
Project-URL: Documentation, https://sqldbclient.readthedocs.io/
Project-URL: Release Notes, https://sqldbclient.readthedocs.io/en/latest/changes.html
Project-URL: Source, https://github.com/YuriyKozhev/sqldbclient
Project-URL: Tracker, https://github.com/YuriyKozhev/sqldbclient/issues
Platform: any
Classifier: Programming Language :: Python :: 3
Classifier: License :: OSI Approved :: MIT License
Classifier: Operating System :: OS Independent
Requires-Python: >=3.6
License-File: LICENSE
Requires-Dist: pandas
Requires-Dist: sqlalchemy
Requires-Dist: sqlparse
Provides-Extra: jupyter
Requires-Dist: jupyter ; extra == 'jupyter'
Requires-Dist: notebook ; extra == 'jupyter'
Requires-Dist: ipykernel ; extra == 'jupyter'
